issue_tracker/__init__.py
issue_tracker/admin.py
issue_tracker/app_settings.py
issue_tracker/apps.py
issue_tracker/middleware.py
issue_tracker/models.py
issue_tracker/channels/__init__.py
issue_tracker/channels/channel.py
issue_tracker/channels/channels_factory.py
issue_tracker/channels/backends/__init__.py
issue_tracker/channels/backends/db.py
issue_tracker/channels/backends/discord.py
issue_tracker/channels/backends/email.py
issue_tracker/channels/backends/slack.py
issue_tracker/channels/backends/teams.py
issue_tracker/migrations/0001_initial.py
issue_tracker/migrations/0002_remove_issue_content_type_remove_issue_user.py
issue_tracker/migrations/__init__.py
issue_tracker/templates/issue_notifire.html
issue_tracker/tests/__init__.py
issue_tracker/tests/conftest.py
issue_tracker/tests/test_channels_factory.py
issue_tracker/tests/channels/__init__.py
issue_tracker/tests/channels/test_app_settings.py
issue_tracker/tests/channels/test_channel.py
issue_tracker/tests/channels/test_middleware.py
issue_tracker/tests/channels/backends/__init__.py
issue_tracker/tests/channels/backends/test_discord.py
issue_tracker/tests/channels/backends/test_teams.py
pys_django_issue_tracker-1.0.2.dist-info/LICENSE.txt
pys_django_issue_tracker-1.0.2.dist-info/METADATA
pys_django_issue_tracker-1.0.2.dist-info/WHEEL
pys_django_issue_tracker-1.0.2.dist-info/top_level.txt
pys_django_issue_tracker-1.0.2.dist-info/RECORD
