Metadata-Version: 2.1
Name: pys-django-issue-tracker
Version: 1.0.2
Summary: Django Issue tracker
Home-page: https://github.com/pys-info/pys-issue-tracker
Author: Pysquad
Author-email: vh@pysquad.com
Project-URL: Bug Reports, https://github.com/pys-info/pys-issue-tracker/issues
Project-URL: Source, https://github.com/pys-info/pys-issue-tracker
Keywords: django,issue,tracker,development
Classifier: Development Status :: 5 - Production/Stable
Classifier: Intended Audience :: Developers
Classifier: Topic :: Software Development :: Build Tools
Classifier: License :: OSI Approved :: MIT License
Classifier: Environment :: Web Environment
Classifier: Operating System :: OS Independent
Classifier: Programming Language :: Python :: 3.5
Classifier: Programming Language :: Python :: 3.6
Classifier: Programming Language :: Python :: 3.7
Classifier: Programming Language :: Python :: 3.8
Classifier: Programming Language :: Python :: 3.9
Classifier: Programming Language :: Python :: 3.10
Classifier: Programming Language :: Python :: 3 :: Only
Classifier: Framework :: Django
Classifier: Framework :: Django :: 3.0
Classifier: Framework :: Django :: 3.1
Classifier: Framework :: Django :: 3.2
Classifier: Framework :: Django :: 4.0
Classifier: Framework :: Django :: 4.1
Classifier: Framework :: Django :: 4.2
Requires-Python: >=3.5
License-File: LICENSE.txt
Requires-Dist: asgiref (==3.6.0)
Requires-Dist: certifi (==2023.5.7)
Requires-Dist: cfgv (==3.3.1)
Requires-Dist: charset-normalizer (==3.1.0)
Requires-Dist: coverage (==7.2.5)
Requires-Dist: discord-webhook (==1.1.0)
Requires-Dist: distlib (==0.3.6)
Requires-Dist: Django (==4.2.1)
Requires-Dist: exceptiongroup (==1.1.1)
Requires-Dist: filelock (==3.12.0)
Requires-Dist: identify (==2.5.24)
Requires-Dist: idna (==3.4)
Requires-Dist: iniconfig (==2.0.0)
Requires-Dist: mocker (==1.1.1)
Requires-Dist: nodeenv (==1.8.0)
Requires-Dist: packaging (==23.1)
Requires-Dist: platformdirs (==3.5.1)
Requires-Dist: pluggy (==1.0.0)
Requires-Dist: pre-commit (==3.3.2)
Requires-Dist: pymsteams (==0.2.2)
Requires-Dist: pytest (==7.3.1)
Requires-Dist: pytest-cov (==4.0.0)
Requires-Dist: pytest-django (==4.5.2)
Requires-Dist: python-dotenv (==1.0.0)
Requires-Dist: PyYAML (==6.0)
Requires-Dist: requests (==2.30.0)
Requires-Dist: slack-sdk (==3.21.3)
Requires-Dist: sqlparse (==0.4.4)
Requires-Dist: timestamp (==0.0.1)
Requires-Dist: tomli (==2.0.1)
Requires-Dist: urllib3 (==2.0.2)
Requires-Dist: virtualenv (==20.23.0)
